confclient/__init__.py
confclient/client.py
confclient/confexcept.py
confclient/restclient.py
confclient/rpcclient.py
confapi-0.2.dist-info/LICENSE
confapi-0.2.dist-info/METADATA
confapi-0.2.dist-info/WHEEL
confapi-0.2.dist-info/top_level.txt
confapi-0.2.dist-info/RECORD
