Metadata-Version: 2.1
Name: confapi
Version: 0.2
Home-page: https://github.com/illini-motorsports/confapi
Author: cmmeyer1800
Author-email: collinmmeyer@gmail.com
Requires-Python: >=3.8
License-File: LICENSE
Requires-Dist: requests (>=2.31.0)
Requires-Dist: PyYAML (>=6.0)
